matplotlib_visual/__init__.py
matplotlib_visual/models.py
matplotlib_visual/code_snippets/__init__.py
matplotlib_visual/code_snippets/ir1.py
matplotlib_visual/code_snippets/ir2.py
matplotlib_visual/code_snippets/ir3.py
matplotlib_visual/code_snippets/ir4.py
matplotlib_visual/code_snippets/ml1.py
matplotlib_visual/code_snippets/ml3.py
matplotlib_visual/code_snippets/ml4.py
matplotlib_visual/code_snippets/pcd2.py
matplotlib_visual/code_snippets/sample.py
matplotlib_plotter-0.1.dist-info/LICENSE
matplotlib_plotter-0.1.dist-info/METADATA
matplotlib_plotter-0.1.dist-info/WHEEL
matplotlib_plotter-0.1.dist-info/top_level.txt
matplotlib_plotter-0.1.dist-info/RECORD
