Metadata-Version: 2.1
Name: matplotlib_plotter
Version: 0.1
Summary: A package for visualizing data using Matplotlib
Author: mcafin44
Author-email: johnmecafin44@gmail.com
License: GPL 3.0
License-File: LICENSE
